mmf_cli/hm_convert.py
mmf_cli/run.py
mmf_cli/__init__.py
mmf_cli/predict.py
mmf/__init__.py
mmf/version.py
mmf/trainers/base_trainer.py
mmf/trainers/__init__.py
mmf/modules/metrics.py
mmf/modules/fusions.py
mmf/modules/embeddings.py
mmf/modules/optimizers.py
mmf/modules/decoders.py
mmf/modules/attention.py
mmf/modules/layers.py
mmf/modules/__init__.py
mmf/modules/losses.py
mmf/modules/schedulers.py
mmf/modules/encoders.py
mmf/utils/download.py
mmf/utils/visualize.py
mmf/utils/general.py
mmf/utils/transform.py
mmf/utils/early_stopping.py
mmf/utils/file_io.py
mmf/utils/dataset.py
mmf/utils/configuration.py
mmf/utils/__init__.py
mmf/utils/process_answers.py
mmf/utils/logger.py
mmf/utils/build.py
mmf/utils/m4c_evaluators.py
mmf/utils/vocab.py
mmf/utils/text.py
mmf/utils/timer.py
mmf/utils/env.py
mmf/utils/distributed.py
mmf/utils/modeling.py
mmf/utils/checkpoint.py
mmf/utils/flags.py
mmf/utils/phoc/__init__.py
mmf/utils/phoc/cphoc.cpython-38-x86_64-linux-gnu.so
mmf/utils/phoc/cphoc.cpython-36m-x86_64-linux-gnu.so
mmf/utils/phoc/cphoc.so
mmf/utils/phoc/build_phoc.py
mmf/utils/phoc/src/cphoc.c
mmf/common/meter.py
mmf/common/sample.py
mmf/common/constants.py
mmf/common/typings.py
mmf/common/__init__.py
mmf/common/registry.py
mmf/common/dataset_loader.py
mmf/common/batch_collator.py
mmf/common/test_reporter.py
mmf/common/report.py
mmf/models/fusions.py
mmf/models/m4c.py
mmf/models/cnn_lstm.py
mmf/models/mmbt.py
mmf/models/butd.py
mmf/models/mmf_bert.py
mmf/models/__init__.py
mmf/models/top_down_bottom_up.py
mmf/models/base_model.py
mmf/models/unimodal.py
mmf/models/pythia.py
mmf/models/visual_bert.py
mmf/models/vilbert.py
mmf/models/visdial_multi_modal.py
mmf/models/lorra.py
mmf/models/m4c_captioner.py
mmf/models/ban.py
mmf/models/interfaces/mmbt.py
mmf/models/interfaces/__init__.py
mmf/datasets/base_dataset_builder.py
mmf/datasets/mmf_dataset.py
mmf/datasets/concat_dataset.py
mmf-1.0.0rc10.dist-info/WHEEL
mmf-1.0.0rc10.dist-info/entry_points.txt
mmf-1.0.0rc10.dist-info/METADATA
mmf-1.0.0rc10.dist-info/NOTICES
mmf-1.0.0rc10.dist-info/top_level.txt
mmf-1.0.0rc10.dist-info/LICENSE
mmf-1.0.0rc10.dist-info/RECORD
