Metadata-Version: 2.1
Name: mmf
Version: 1.0.0rc10
Summary: mmf: a modular framework for vision and language multimodal research.
Home-page: UNKNOWN
Author: Facebook AI Research
Author-email: mmf@fb.com
License: UNKNOWN
Platform: UNKNOWN
Classifier: Programming Language :: Python :: 3.6
Classifier: Programming Language :: Python :: 3.7
Classifier: Programming Language :: Python :: 3.8
Classifier: License :: OSI Approved :: BSD License
Classifier: Topic :: Scientific/Engineering :: Artificial Intelligence
Classifier: Operating System :: OS Independent
Requires-Python: >=3.6
Requires-Dist: torch (==1.5.0)
Requires-Dist: torchvision (==0.6.0)
Requires-Dist: numpy (>=1.16.6)
Requires-Dist: tqdm (>=4.43.0)
Requires-Dist: demjson (==2.2.4)
Requires-Dist: torchtext (==0.5.0)
Requires-Dist: GitPython (==3.1.0)
Requires-Dist: requests (==2.23.0)
Requires-Dist: fasttext (==0.9.1)
Requires-Dist: nltk (==3.4.5)
Requires-Dist: editdistance (==0.5.3)
Requires-Dist: transformers (==2.3.0)
Requires-Dist: sklearn (==0.0)
Requires-Dist: omegaconf (==2.0.1rc4)
Requires-Dist: lmdb (==0.98)
